osvc_python/__init__.py
osvc_python/osvc_python_analytics_report_results.py
osvc_python/osvc_python_client.py
osvc_python/osvc_python_config.py
osvc_python/osvc_python_connect.py
osvc_python/osvc_python_examples.py
osvc_python/osvc_python_file_handling.py
osvc_python/osvc_python_normalize.py
osvc_python/osvc_python_query_results.py
osvc_python/osvc_python_query_results_set.py
osvc_python/osvc_python_response.py
osvc_python/osvc_python_validations.py
osvc_python/test_osvc_python_analytics_report_results.py
osvc_python/test_osvc_python_client.py
osvc_python/test_osvc_python_connect.py
osvc_python/test_osvc_python_query_results.py
osvc_python/test_osvc_python_query_results_set.py
osvc_python/test_osvc_python_response.py
osvc_python/test_osvc_python_validations.py
osvc_python-1.0.1.dist-info/DESCRIPTION.rst
osvc_python-1.0.1.dist-info/METADATA
osvc_python-1.0.1.dist-info/RECORD
osvc_python-1.0.1.dist-info/WHEEL
osvc_python-1.0.1.dist-info/metadata.json
osvc_python-1.0.1.dist-info/top_level.txt
