Metadata-Version: 2.0
Name: osvc-python
Version: 1.0.1
Summary: An unofficial Python wrapper on top of the Oracle Cloud Services (fka RightNow Technologies) REST API
Home-page: http://github.com/rajangdavis/osvc_python
Author: Rajan Davis
Author-email: rajangdavis@gmail.com
License: MIT
Platform: UNKNOWN
Requires-Dist: requests
Requires-Dist: futures
